pymacro/__init__.py
pymacro/effects.py
pymacro/errors.py
pymacro/macro.py
pymacro/ui.py
pymacro/util.py
pymacro-0.1.1.dist-info/METADATA
pymacro-0.1.1.dist-info/WHEEL
pymacro-0.1.1.dist-info/top_level.txt
pymacro-0.1.1.dist-info/RECORD
