Metadata-Version: 2.1
Name: pymacro
Version: 0.1.1
Summary: PyMacro can automate your tasks inside of Python.
Home-page: https://github.com/jay3332/PyMacro
Author: jay3332
License: UNKNOWN
Platform: UNKNOWN
Classifier: Programming Language :: Python :: 3
Classifier: License :: OSI Approved :: MIT License
Classifier: Operating System :: OS Independent
Requires-Dist: pyautogui
Requires-Dist: pytweening
